Workbook

Sheet Stakeholders
A1: 🏗 PROJECT STAKEHOLDERS & PROFIT CONFIGURATION
A2: Stakeholder Name | B2: Role / Company | C2: Contact | D2: Notes | E2: Fixed Split % | F2: Profit Share | G2: Total Contributed | H2: Settlement
A13: TOTALS | E13: =SUM(E3:E12) -> 0 | F13: =SUM(F3:F12) -> 0 | G13: =SUM(G3:G12) -> 0 | H13: =SUM(H3:H12) -> 0
A14: =IF(ABS(SUM(E3:E12)-1)<0.001,"✔ Fixed Split % totals 100% — OK","⚠ WARNING: Split % = "&TEXT(SUM(E3:E12),"0%")&" — must equal exactly 100%") -> ⚠ WARNING: Split % = 0% — must equal exactly 100%
A15: ℹ Rows 3–12 support up to 10 stakeholders. Enter name + Fixed Split %. Columns F–H are auto-calculated. Blue cells = user input.

Sheet Expenses
A1: 🏗 DAILY CONSTRUCTION EXPENSE LOG
A2: Enter one expense per row. Type any category. Split amounts across stakeholders (cols F–O). Split Check column auto-validates totals.
A3: Date | B3: Expense ID | C3: Description | D3: Category | E3: Total Expense | F3: =IF(Stakeholders!A3<>"",Stakeholders!A3,"Stakeholder "&1) -> Stakeholder 1 | G3: =IF(Stakeholders!A4<>"",Stakeholders!A4,"Stakeholder "&2) -> Stakeholder 2 | H3: =IF(Stakeholders!A5<>"",Stakeholders!A5,"Stakeholder "&3) -> Stakeholder 3 | I3: =IF(Stakeholders!A6<>"",Stakeholders!A6,"Stakeholder "&4) -> Stakeholder 4 | J3: =IF(Stakeholders!A7<>"",Stakeholders!A7,"Stakeholder "&5) -> Stakeholder 5 | K3: =IF(Stakeholders!A8<>"",Stakeholders!A8,"Stakeholder "&6) -> Stakeholder 6 | L3: =IF(Stakeholders!A9<>"",Stakeholders!A9,"Stakeholder "&7) -> Stakeholder 7 | M3: =IF(Stakeholders!A10<>"",Stakeholders!A10,"Stakeholder "&8) -> Stakeholder 8 | N3: =IF(Stakeholders!A11<>"",Stakeholders!A11,"Stakeholder "&9) -> Stakeholder 9 | O3: =IF(Stakeholders!A12<>"",Stakeholders!A12,"Stakeholder "&10) -> Stakeholder 10 | P3: Split Check | Q3: Receipt # | R3: Payment Method | S3: Notes
P4: =IF(E4=0,"-",IF(ABS(E4-(F4+G4+H4+I4+J4+K4+L4+M4+N4+O4))<0.01,"✔ OK","⚠ Mismatch")) -> -
P5: =IF(E5=0,"-",IF(ABS(E5-(F5+G5+H5+I5+J5+K5+L5+M5+N5+O5))<0.01,"✔ OK","⚠ Mismatch")) -> -
P6: =IF(E6=0,"-",IF(ABS(E6-(F6+G6+H6+I6+J6+K6+L6+M6+N6+O6))<0.01,"✔ OK","⚠ Mismatch")) -> -
P7: =IF(E7=0,"-",IF(ABS(E7-(F7+G7+H7+I7+J7+K7+L7+M7+N7+O7))<0.01,"✔ OK","⚠ Mismatch")) -> -
P8: =IF(E8=0,"-",IF(ABS(E8-(F8+G8+H8+I8+J8+K8+L8+M8+N8+O8))<0.01,"✔ OK","⚠ Mismatch")) -> -
P9: =IF(E9=0,"-",IF(ABS(E9-(F9+G9+H9+I9+J9+K9+L9+M9+N9+O9))<0.01,"✔ OK","⚠ Mismatch")) -> -
P10: =IF(E10=0,"-",IF(ABS(E10-(F10+G10+H10+I10+J10+K10+L10+M10+N10+O10))<0.01,"✔ OK","⚠ Mismatch")) -> -
P11: =IF(E11=0,"-",IF(ABS(E11-(F11+G11+H11+I11+J11+K11+L11+M11+N11+O11))<0.01,"✔ OK","⚠ Mismatch")) -> -
P12: =IF(E12=0,"-",IF(ABS(E12-(F12+G12+H12+I12+J12+K12+L12+M12+N12+O12))<0.01,"✔ OK","⚠ Mismatch")) -> -
P13: =IF(E13=0,"-",IF(ABS(E13-(F13+G13+H13+I13+J13+K13+L13+M13+N13+O13))<0.01,"✔ OK","⚠ Mismatch")) -> -
P14: =IF(E14=0,"-",IF(ABS(E14-(F14+G14+H14+I14+J14+K14+L14+M14+N14+O14))<0.01,"✔ OK","⚠ Mismatch")) -> -
P15: =IF(E15=0,"-",IF(ABS(E15-(F15+G15+H15+I15+J15+K15+L15+M15+N15+O15))<0.01,"✔ OK","⚠ Mismatch")) -> -
... P1003: =IF(E1003=0,"-",IF(ABS(E1003-(F1003+G1003+H1003+I1003+J1003+K1003+L1003+M1003+N1003+O1003))<0.01,"✔ OK","⚠ Mismatch")) -> -

Sheet Dashboard
A1: 🏗 CONSTRUCTION PROJECT — MANAGEMENT DASHBOARD
A3: 📊 PROJECT SNAPSHOT | I3: 💰 PROFIT SUMMARY
A4: Total Project Spend | E4: =SUM(Expenses!E4:E1003) -> 0 | I4: Sale Price | M4: =E13
A5: Project Sale Price | I5: Total Project Cost | M5: =E4 -> 0
A6: Gross Profit | I6: Gross Profit | M6: =E6
A7: Net Profit Margin | E7: =IFERROR(E6/E13,0) -> 0 | I7: Net Profit Margin | M7: =E7 -> 0
A8: Total Expenses Logged | E8: =COUNTA(Expenses!B4:B1003) -> 0 | I8: Split % Validated | M8: =IF(ABS(SUM(Stakeholders!E3:E12)-1)<0.001,"✔ 100%","⚠ Check") -> ⚠ Check
A9: Avg Expense per Entry | E9: =IFERROR(B4/B8,0) -> 0
A10: Split Mismatches | E10: =COUNTIF(Expenses!P4:P1003,"⚠ Mismatch") -> 0
A11: Outstanding Splits
A13: 💰 PROJECT SALE PRICE (enter value →)
I15: 📂 SPEND BY CATEGORY
A16: 👥 STAKEHOLDER CONTRIBUTIONS | I16: Category | M16: Total | O16: % Share | P16: # Entries
A17: Stakeholder | B17: Split % | C17: Contributed | D17: Profit Share | E17: Settlement | F17: Status | I17: Materials | M17: =SUMIF(Expenses!D4:D1003,I17,Expenses!E4:E1003) -> 0 | O17: =IFERROR(M17/E4,0) -> 0 | P17: =COUNTIF(Expenses!D4:D1003,I17) -> 0
A18: =IF(Stakeholders!A3<>"",Stakeholders!A3,"—") -> — | B18: =Stakeholders!E3 | C18: =SUM(Expenses!F4:F1003) -> 0 | D18: =IFERROR(E6*Stakeholders!E3,0) -> 0 | E18: =D18-C18 -> 0 | F18: =IF(Stakeholders!A3="","—",IF(D18>C18,"✔ Profit Due","⚠ Shortfall")) -> — | I18: Labour | M18: =SUMIF(Expenses!D4:D1003,I18,Expenses!E4:E1003) -> 0 | O18: =IFERROR(M18/E4,0) -> 0 | P18: =COUNTIF(Expenses!D4:D1003,I18) -> 0
A19: =IF(Stakeholders!A4<>"",Stakeholders!A4,"—") -> — | B19: =Stakeholders!E4 | C19: =SUM(Expenses!G4:G1003) -> 0 | D19: =IFERROR(E6*Stakeholders!E4,0) -> 0 | E19: =D19-C19 -> 0 | F19: =IF(Stakeholders!A4="","—",IF(D19>C19,"✔ Profit Due","⚠ Shortfall")) -> — | I19: Transport | M19: =SUMIF(Expenses!D4:D1003,I19,Expenses!E4:E1003) -> 0 | O19: =IFERROR(M19/E4,0) -> 0 | P19: =COUNTIF(Expenses!D4:D1003,I19) -> 0
A20: =IF(Stakeholders!A5<>"",Stakeholders!A5,"—") -> — | B20: =Stakeholders!E5 | C20: =SUM(Expenses!H4:H1003) -> 0 | D20: =IFERROR(E6*Stakeholders!E5,0) -> 0 | E20: =D20-C20 -> 0 | F20: =IF(Stakeholders!A5="","—",IF(D20>C20,"✔ Profit Due","⚠ Shortfall")) -> — | I20: Permits & Fees | M20: =SUMIF(Expenses!D4:D1003,I20,Expenses!E4:E1003) -> 0 | O20: =IFERROR(M20/E4,0) -> 0 | P20: =COUNTIF(Expenses!D4:D1003,I20) -> 0
A21: =IF(Stakeholders!A6<>"",Stakeholders!A6,"—") -> — | B21: =Stakeholders!E6 | C21: =SUM(Expenses!I4:I1003) -> 0 | D21: =IFERROR(E6*Stakeholders!E6,0) -> 0 | E21: =D21-C21 -> 0 | F21: =IF(Stakeholders!A6="","—",IF(D21>C21,"✔ Profit Due","⚠ Shortfall")) -> — | I21: Equipment Rental | M21: =SUMIF(Expenses!D4:D1003,I21,Expenses!E4:E1003) -> 0 | O21: =IFERROR(M21/E4,0) -> 0 | P21: =COUNTIF(Expenses!D4:D1003,I21) -> 0
A22: =IF(Stakeholders!A7<>"",Stakeholders!A7,"—") -> — | B22: =Stakeholders!E7 | C22: =SUM(Expenses!J4:J1003) -> 0 | D22: =IFERROR(E6*Stakeholders!E7,0) -> 0 | E22: =D22-C22 -> 0 | F22: =IF(Stakeholders!A7="","—",IF(D22>C22,"✔ Profit Due","⚠ Shortfall")) -> — | I22: Subcontractors | M22: =SUMIF(Expenses!D4:D1003,I22,Expenses!E4:E1003) -> 0 | O22: =IFERROR(M22/E4,0) -> 0 | P22: =COUNTIF(Expenses!D4:D1003,I22) -> 0
A23: =IF(Stakeholders!A8<>"",Stakeholders!A8,"—") -> — | B23: =Stakeholders!E8 | C23: =SUM(Expenses!K4:K1003) -> 0 | D23: =IFERROR(E6*Stakeholders!E8,0) -> 0 | E23: =D23-C23 -> 0 | F23: =IF(Stakeholders!A8="","—",IF(D23>C23,"✔ Profit Due","⚠ Shortfall")) -> — | I23: Site Overhead | M23: =SUMIF(Expenses!D4:D1003,I23,Expenses!E4:E1003) -> 0 | O23: =IFERROR(M23/E4,0) -> 0 | P23: =COUNTIF(Expenses!D4:D1003,I23) -> 0
A24: =IF(Stakeholders!A9<>"",Stakeholders!A9,"—") -> — | B24: =Stakeholders!E9 | C24: =SUM(Expenses!L4:L1003) -> 0 | D24: =IFERROR(E6*Stakeholders!E9,0) -> 0 | E24: =D24-C24 -> 0 | F24: =IF(Stakeholders!A9="","—",IF(D24>C24,"✔ Profit Due","⚠ Shortfall")) -> — | I24: Safety & PPE | M24: =SUMIF(Expenses!D4:D1003,I24,Expenses!E4:E1003) -> 0 | O24: =IFERROR(M24/E4,0) -> 0 | P24: =COUNTIF(Expenses!D4:D1003,I24) -> 0
A25: =IF(Stakeholders!A10<>"",Stakeholders!A10,"—") -> — | B25: =Stakeholders!E10 | C25: =SUM(Expenses!M4:M1003) -> 0 | D25: =IFERROR(E6*Stakeholders!E10,0) -> 0 | E25: =D25-C25 -> 0 | F25: =IF(Stakeholders!A10="","—",IF(D25>C25,"✔ Profit Due","⚠ Shortfall")) -> — | I25: Professional Fees | M25: =SUMIF(Expenses!D4:D1003,I25,Expenses!E4:E1003) -> 0 | O25: =IFERROR(M25/E4,0) -> 0 | P25: =COUNTIF(Expenses!D4:D1003,I25) -> 0
A26: =IF(Stakeholders!A11<>"",Stakeholders!A11,"—") -> — | B26: =Stakeholders!E11 | C26: =SUM(Expenses!N4:N1003) -> 0 | D26: =IFERROR(E6*Stakeholders!E11,0) -> 0 | E26: =D26-C26 -> 0 | F26: =IF(Stakeholders!A11="","—",IF(D26>C26,"✔ Profit Due","⚠ Shortfall")) -> — | I26: Utilities | M26: =SUMIF(Expenses!D4:D1003,I26,Expenses!E4:E1003) -> 0 | O26: =IFERROR(M26/E4,0) -> 0 | P26: =COUNTIF(Expenses!D4:D1003,I26) -> 0
A27: =IF(Stakeholders!A12<>"",Stakeholders!A12,"—") -> — | B27: =Stakeholders!E12 | C27: =SUM(Expenses!O4:O1003) -> 0 | D27: =IFERROR(E6*Stakeholders!E12,0) -> 0 | E27: =D27-C27 -> 0 | F27: =IF(Stakeholders!A12="","—",IF(D27>C27,"✔ Profit Due","⚠ Shortfall")) -> — | I27: Miscellaneous | M27: =SUMIF(Expenses!D4:D1003,I27,Expenses!E4:E1003) -> 0 | O27: =IFERROR(M27/E4,0) -> 0 | P27: =COUNTIF(Expenses!D4:D1003,I27) -> 0
A28: TOTALS | C28: =SUM(C18:C27) -> 0 | D28: =SUM(D18:D27) -> 0 | E28: =SUM(E18:E27) -> 0 | I28: TOTAL | M28: =SUM(M17:M27) -> 0
A30: 🧾 EXPENSE SETTLEMENT SUMMARY
A31: Stakeholder | B31: Expenses Paid | C31: Share of Cost | D31: Over/Under-Paid | E31: To Pay / Receive | F31: Settled?
A32: =IF(Stakeholders!A3<>"",Stakeholders!A3,"—") -> — | B32: =SUM(Expenses!F4:F1003) -> 0 | C32: =IFERROR(E4*Stakeholders!E3,0) -> 0 | D32: =B32-C32 -> 0 | E32: =IF(D32>0,"Receive "&TEXT(D32,"#,##0.00"),IF(D32<0,"Pay "&TEXT(ABS(D32),"#,##0.00"),"Settled")) -> Settled | F32: =IF(ABS(D32)<0.01,"✔ Even","⚠ Pending") -> ✔ Even
A33: =IF(Stakeholders!A4<>"",Stakeholders!A4,"—") -> — | B33: =SUM(Expenses!G4:G1003) -> 0 | C33: =IFERROR(E4*Stakeholders!E4,0) -> 0 | D33: =B33-C33 -> 0 | E33: =IF(D33>0,"Receive "&TEXT(D33,"#,##0.00"),IF(D33<0,"Pay "&TEXT(ABS(D33),"#,##0.00"),"Settled")) -> Settled | F33: =IF(ABS(D33)<0.01,"✔ Even","⚠ Pending") -> ✔ Even
A34: =IF(Stakeholders!A5<>"",Stakeholders!A5,"—") -> — | B34: =SUM(Expenses!H4:H1003) -> 0 | C34: =IFERROR(E4*Stakeholders!E5,0) -> 0 | D34: =B34-C34 -> 0 | E34: =IF(D34>0,"Receive "&TEXT(D34,"#,##0.00"),IF(D34<0,"Pay "&TEXT(ABS(D34),"#,##0.00"),"Settled")) -> Settled | F34: =IF(ABS(D34)<0.01,"✔ Even","⚠ Pending") -> ✔ Even
A35: =IF(Stakeholders!A6<>"",Stakeholders!A6,"—") -> — | B35: =SUM(Expenses!I4:I1003) -> 0 | C35: =IFERROR(E4*Stakeholders!E6,0) -> 0 | D35: =B35-C35 -> 0 | E35: =IF(D35>0,"Receive "&TEXT(D35,"#,##0.00"),IF(D35<0,"Pay "&TEXT(ABS(D35),"#,##0.00"),"Settled")) -> Settled | F35: =IF(ABS(D35)<0.01,"✔ Even","⚠ Pending") -> ✔ Even
A36: =IF(Stakeholders!A7<>"",Stakeholders!A7,"—") -> — | B36: =SUM(Expenses!J4:J1003) -> 0 | C36: =IFERROR(E4*Stakeholders!E7,0) -> 0 | D36: =B36-C36 -> 0 | E36: =IF(D36>0,"Receive "&TEXT(D36,"#,##0.00"),IF(D36<0,"Pay "&TEXT(ABS(D36),"#,##0.00"),"Settled")) -> Settled | F36: =IF(ABS(D36)<0.01,"✔ Even","⚠ Pending") -> ✔ Even
A37: =IF(Stakeholders!A8<>"",Stakeholders!A8,"—") -> — | B37: =SUM(Expenses!K4:K1003) -> 0 | C37: =IFERROR(E4*Stakeholders!E8,0) -> 0 | D37: =B37-C37 -> 0 | E37: =IF(D37>0,"Receive "&TEXT(D37,"#,##0.00"),IF(D37<0,"Pay "&TEXT(ABS(D37),"#,##0.00"),"Settled")) -> Settled | F37: =IF(ABS(D37)<0.01,"✔ Even","⚠ Pending") -> ✔ Even
A38: =IF(Stakeholders!A9<>"",Stakeholders!A9,"—") -> — | B38: =SUM(Expenses!L4:L1003) -> 0 | C38: =IFERROR(E4*Stakeholders!E9,0) -> 0 | D38: =B38-C38 -> 0 | E38: =IF(D38>0,"Receive "&TEXT(D38,"#,##0.00"),IF(D38<0,"Pay "&TEXT(ABS(D38),"#,##0.00"),"Settled")) -> Settled | F38: =IF(ABS(D38)<0.01,"✔ Even","⚠ Pending") -> ✔ Even
A39: =IF(Stakeholders!A10<>"",Stakeholders!A10,"—") -> — | B39: =SUM(Expenses!M4:M1003) -> 0 | C39: =IFERROR(E4*Stakeholders!E10,0) -> 0 | D39: =B39-C39 -> 0 | E39: =IF(D39>0,"Receive "&TEXT(D39,"#,##0.00"),IF(D39<0,"Pay "&TEXT(ABS(D39),"#,##0.00"),"Settled")) -> Settled | F39: =IF(ABS(D39)<0.01,"✔ Even","⚠ Pending") -> ✔ Even
A40: =IF(Stakeholders!A11<>"",Stakeholders!A11,"—") -> — | B40: =SUM(Expenses!N4:N1003) -> 0 | C40: =IFERROR(E4*Stakeholders!E11,0) -> 0 | D40: =B40-C40 -> 0 | E40: =IF(D40>0,"Receive "&TEXT(D40,"#,##0.00"),IF(D40<0,"Pay "&TEXT(ABS(D40),"#,##0.00"),"Settled")) -> Settled | F40: =IF(ABS(D40)<0.01,"✔ Even","⚠ Pending") -> ✔ Even
A41: =IF(Stakeholders!A12<>"",Stakeholders!A12,"—") -> — | B41: =SUM(Expenses!O4:O1003) -> 0 | C41: =IFERROR(E4*Stakeholders!E12,0) -> 0 | D41: =B41-C41 -> 0 | E41: =IF(D41>0,"Receive "&TEXT(D41,"#,##0.00"),IF(D41<0,"Pay "&TEXT(ABS(D41),"#,##0.00"),"Settled")) -> Settled | F41: =IF(ABS(D41)<0.01,"✔ Even","⚠ Pending") -> ✔ Even
A42: TOTALS | C42: =SUM(C32:C41) -> 0 | D42: =SUM(D32:D41) -> 0
